lerxmlspy/__init__.py
lerxmlspy/lerxmlspy.py
lerxmlspy-0.0.2.dist-info/METADATA
lerxmlspy-0.0.2.dist-info/WHEEL
lerxmlspy-0.0.2.dist-info/top_level.txt
lerxmlspy-0.0.2.dist-info/RECORD
