Metadata-Version: 2.1
Name: lerxmlspy
Version: 0.0.2
Summary: Um pacote para leitura de arquivos XML e converter para DataFrames
Home-page: https://github.com/RoSchilling/lerxmlspy
Author: Rodrigo Schilling
Author-email: rodrigo.schilling98@gmail.com
Requires-Dist: xmltodict
Requires-Dist: pandas
Requires-Dist: lxml
